mangleddlt-0.1.4.dist-info/licenses/LICENSE
mangledlt/__init__.py
mangledlt/config.py
mangledlt/dlt.py
mangledlt/exceptions.py
mangledlt/auth/__init__.py
mangledlt/auth/databricks_cli.py
mangledlt/cache/__init__.py
mangledlt/cache/query_cache.py
mangledlt/cli/__init__.py
mangledlt/cli/main.py
mangledlt/cli/scaffold.py
mangledlt/cli/templates/Transformations/table_example.py
mangledlt/cli/templates/Transformations/view_example.py
mangledlt/connectors/__init__.py
mangledlt/connectors/unity_catalog.py
mangledlt/core/__init__.py
mangledlt/core/connection_pool.py
mangledlt/core/display.py
mangledlt/core/interceptor.py
mangledlt/core/session.py
mangledlt/dbutils/__init__.py
mangledlt/dbutils/dbutils_wrapper.py
mangledlt/models/__init__.py
mangledlt/models/catalog_reference.py
mangledlt/models/databricks_config.py
mangledlt/models/intercepted_dataframe.py
mangledlt/models/unity_catalog_connection.py
mangledlt/utils/__init__.py
mangledlt/utils/error_handler.py
mangledlt/utils/parser.py
mangleddlt-0.1.4.dist-info/METADATA
mangleddlt-0.1.4.dist-info/WHEEL
mangleddlt-0.1.4.dist-info/entry_points.txt
mangleddlt-0.1.4.dist-info/top_level.txt
mangleddlt-0.1.4.dist-info/RECORD
