Metadata-Version: 2.4
Name: MangledDlt
Version: 0.1.4
Summary: Local Databricks Development Bridge - Intercept Spark operations for local Unity Catalog access
Home-page: https://github.com/mangledlt/mangledlt
Author: MangledDLT Team
Author-email: MangledDLT Team <mangler@mangledinnovation.com>
License: MIT
Project-URL: Homepage, https://github.com/mangledlt/mangledlt
Project-URL: Bug Tracker, https://github.com/mangledlt/mangledlt/issues
Project-URL: Documentation, https://github.com/mangledlt/mangledlt/docs
Classifier: Development Status :: 3 - Alpha
Classifier: Intended Audience :: Developers
Classifier: License :: OSI Approved :: MIT License
Classifier: Programming Language :: Python :: 3
Classifier: Programming Language :: Python :: 3.9
Classifier: Programming Language :: Python :: 3.10
Classifier: Programming Language :: Python :: 3.11
Classifier: Topic :: Software Development :: Libraries :: Python Modules
Requires-Python: >=3.9
License-File: LICENSE
Requires-Dist: databricks-sql-connector>=2.9.0
Requires-Dist: databricks-sdk>=0.20.0
Requires-Dist: configparser>=5.0
Requires-Dist: python-dotenv>=1.0.0
Requires-Dist: pyspark>=3.4.0
Provides-Extra: all
Provides-Extra: dev
Requires-Dist: pytest>=7.0; extra == "dev"
Requires-Dist: pytest-mock>=3.0; extra == "dev"
Requires-Dist: pytest-cov>=4.0; extra == "dev"
Requires-Dist: black>=23.0; extra == "dev"
Requires-Dist: mypy>=1.0; extra == "dev"
Requires-Dist: coverage>=6.0; extra == "dev"
Dynamic: author
Dynamic: home-page
Dynamic: license-file
Dynamic: requires-python
